rfmodel/__init__.py
rfmodel/read_profile.py
rfmodel/rfmodel.py
rfmodel/rfmodel_types.py
rfmodel/util.py
rfmodel/geod/__init__.py
rfmodel/geod/geod_backport.py
rfmodel/geod/geod_profile.py
RFModel-0.0.9.dist-info/LICENSE
RFModel-0.0.9.dist-info/METADATA
RFModel-0.0.9.dist-info/WHEEL
RFModel-0.0.9.dist-info/top_level.txt
RFModel-0.0.9.dist-info/RECORD
