Metadata-Version: 2.1
Name: RFModel
Version: 0.0.9
Summary: RFModel Python API
Home-page: https://github.com/talos-gis/rfmodel
Author: Idan Miara
Author-email: idan@miara.com
License: MIT
Platform: UNKNOWN
Requires-Dist: numpy
Requires-Dist: gdal (>=3.0.0)
Requires-Dist: gdal-utils (>=3.3.0.7)
Requires-Dist: pyproj (>=3.0.1)
Provides-Extra: tirem
Requires-Dist: tirem ; extra == 'tirem'
